tagify/__init__.py
tagify/parser.py
tagify-0.0.10.dist-info/licenses/LICENSE
tagify-0.0.10.dist-info/METADATA
tagify-0.0.10.dist-info/WHEEL
tagify-0.0.10.dist-info/top_level.txt
tagify-0.0.10.dist-info/RECORD
